{"SURVIVAL":{"armorContents":{"0":{"==":"org.bukkit.inventory.ItemStack","type":"DIAMOND_BOOTS","damage":15,"meta":{"==":"ItemMeta","meta-type":"UNSPECIFIC","display-name":"§6Emerald Boots","lore":[""],"enchants":{"PROTECTION_ENVIRONMENTAL":10,"DURABILITY":10,"PROTECTION_FALL":10}}},"1":{"==":"org.bukkit.inventory.ItemStack","type":"DIAMOND_LEGGINGS","damage":13,"meta":{"==":"ItemMeta","meta-type":"UNSPECIFIC","display-name":"§6Emerald Leggings","lore":[""],"enchants":{"PROTECTION_ENVIRONMENTAL":10,"DURABILITY":10}}},"2":{"==":"org.bukkit.inventory.ItemStack","type":"DIAMOND_CHESTPLATE","damage":27,"meta":{"==":"ItemMeta","meta-type":"UNSPECIFIC","display-name":"§6Emerald Chesplate","lore":[""],"enchants":{"PROTECTION_ENVIRONMENTAL":10,"DURABILITY":10,"THORNS":10}}},"3":{"==":"org.bukkit.inventory.ItemStack","type":"DIAMOND_HELMET","damage":12,"meta":{"==":"ItemMeta","meta-type":"UNSPECIFIC","display-name":"§6Emerald Helmet","lore":[""],"enchants":{"PROTECTION_ENVIRONMENTAL":10,"DURABILITY":10}}}},"enderChestContents":{"0":{"==":"org.bukkit.inventory.ItemStack","type":"GOLD_BLOCK","amount":14},"1":{"==":"org.bukkit.inventory.ItemStack","type":"COOKED_BEEF"},"3":{"==":"org.bukkit.inventory.ItemStack","type":"DIAMOND_PICKAXE","damage":8,"meta":{"==":"ItemMeta","meta-type":"UNSPECIFIC","display-name":"§6Emerald Pickaxe","lore":[""],"enchants":{"DIG_SPEED":10,"DURABILITY":10,"LOOT_BONUS_BLOCKS":10}}},"4":{"==":"org.bukkit.inventory.ItemStack","type":"ARROW","amount":64},"5":{"==":"org.bukkit.inventory.ItemStack","type":"DIAMOND_SWORD","damage":30,"meta":{"==":"ItemMeta","meta-type":"UNSPECIFIC","display-name":"§6Emerald Sword","lore":[""],"enchants":{"DAMAGE_ALL":10,"DURABILITY":10,"FIRE_ASPECT":10,"LOOT_BONUS_MOBS":10}}},"16":{"==":"org.bukkit.inventory.ItemStack","type":"DIAMOND_BLOCK","amount":7},"6":{"==":"org.bukkit.inventory.ItemStack","type":"ARROW","amount":64,"meta":{"==":"ItemMeta","meta-type":"UNSPECIFIC","display-name":"§r§3Daily"}},"18":{"==":"org.bukkit.inventory.ItemStack","type":"ARROW","amount":64,"meta":{"==":"ItemMeta","meta-type":"UNSPECIFIC","display-name":"§r§2Weekly"}},"8":{"==":"org.bukkit.inventory.ItemStack","type":"BOW","meta":{"==":"ItemMeta","meta-type":"UNSPECIFIC","lore":["§bWater-Infused X","§3Speed IX","§5Wither X","§9Ice IX","§4Fire-Infused X"],"enchants":{"ARROW_DAMAGE":3,"DURABILITY":3,"ARROW_FIRE":1}}},"9":{"==":"org.bukkit.inventory.ItemStack","type":"SLIME_BLOCK","amount":64},"10":{"==":"org.bukkit.inventory.ItemStack","type":"GOLDEN_APPLE","damage":1,"amount":52}},"inventoryContents":{},"stats":{"ma":"300","el":"0","xp":"0.0","hp":"20","txp":"0","ft":"-20","fd":"0.0","ra":"300"}}}