{"SURVIVAL":{"inventoryContents":{"0":{"==":"org.bukkit.inventory.ItemStack","type":"WOOD_AXE"},"1":{"==":"org.bukkit.inventory.ItemStack","type":"STONE"},"2":{"==":"org.bukkit.inventory.ItemStack","type":"COBBLESTONE","amount":2},"3":{"==":"org.bukkit.inventory.ItemStack","type":"SMOOTH_BRICK"},"4":{"==":"org.bukkit.inventory.ItemStack","type":"ROTTEN_FLESH","amount":64},"5":{"==":"org.bukkit.inventory.ItemStack","type":"ROTTEN_FLESH","amount":64},"6":{"==":"org.bukkit.inventory.ItemStack","type":"DIAMOND_BLOCK"},"7":{"==":"org.bukkit.inventory.ItemStack","type":"DIAMOND"}},"armorContents":{},"enderChestContents":{"13":{"==":"org.bukkit.inventory.ItemStack","type":"MOB_SPAWNER","meta":{"==":"ItemMeta","meta-type":"TILE_ENTITY","display-name":"§ePig §fSpawner","lore":["entityID:90"],"internal":"H4sIAAAAAAAAAONiYOBi4HPKyU\/Ods0rySypDElM52DggLA9UxiYAzLTgSp4gjNzsoMLEsvzUouKmRg4UiHyLgxRDAwAV4b3DEMAAAA=","blockMaterial":"MOB_SPAWNER"}},"14":{"==":"org.bukkit.inventory.ItemStack","type":"MOB_SPAWNER","meta":{"==":"ItemMeta","meta-type":"TILE_ENTITY","display-name":"§eSheep §fSpawner","lore":["entityID:91"],"internal":"H4sIAAAAAAAAAONiYOBi4HPKyU\/Ods0rySypDElM52DggLA9UxhYgzNSUwuAaniCM3OygwsSy\/NSi4qZGDhSISpcGKIZGAANfr2cRQAAAA==","blockMaterial":"MOB_SPAWNER"}},"25":{"==":"org.bukkit.inventory.ItemStack","type":"GOLDEN_APPLE","damage":1,"amount":54},"15":{"==":"org.bukkit.inventory.ItemStack","type":"MOB_SPAWNER","meta":{"==":"ItemMeta","meta-type":"TILE_ENTITY","display-name":"§eCow §fSpawner","lore":["entityID:92"],"internal":"H4sIAAAAAAAAAONiYOBi4HPKyU\/Ods0rySypDElM52DggLA9UxiYnfPLgSp4gjNzsoMLEsvzUouKmRg4UiHyLgwxDAwA3xw860MAAAA=","blockMaterial":"MOB_SPAWNER"}},"16":{"==":"org.bukkit.inventory.ItemStack","type":"MOB_SPAWNER","meta":{"==":"ItemMeta","meta-type":"TILE_ENTITY","display-name":"§eChicken §fSpawner","lore":["entityID:93"],"internal":"H4sIAAAAAAAAAONiYOBi4HPKyU\/Ods0rySypDElM52DggLA9UxjYnTMyk7NT84CqeIIzc7KDCxLL81KLipkYOFIhalwYYhkYAFCbDKxHAAAA","blockMaterial":"MOB_SPAWNER"}},"17":{"==":"org.bukkit.inventory.ItemStack","type":"WRITTEN_BOOK","meta":{"==":"ItemMeta","meta-type":"BOOK_SIGNED","title":"THE BEAUTY","author":"BagMvision","pages":["FABTASTIC BOOK\\n\\nklik here\\n\\nand here\\n\\n\\nok the book is very ugly ok......"],"generation":0}},"18":{"==":"org.bukkit.inventory.ItemStack","type":"OBSIDIAN"},"19":{"==":"org.bukkit.inventory.ItemStack","type":"REDSTONE_TORCH_ON"},"0":{"==":"org.bukkit.inventory.ItemStack","type":"DIAMOND_SWORD","damage":2,"meta":{"==":"ItemMeta","meta-type":"UNSPECIFIC","lore":["§bWater-Infused IX","§2Poison X","§9Ice X","§4Fire-Infused X"],"enchants":{"DAMAGE_ALL":5,"DURABILITY":3,"KNOCKBACK":2,"FIRE_ASPECT":2,"LOOT_BONUS_MOBS":2},"repair-cost":7}},"1":{"==":"org.bukkit.inventory.ItemStack","type":"BOW","damage":9,"meta":{"==":"ItemMeta","meta-type":"UNSPECIFIC","display-name":"§r§6§lThe§5TOY","lore":["§3Speed IX","§5Wither IX","§9Ice X","§4Fire-Infused IX"],"enchants":{"ARROW_DAMAGE":5,"ARROW_KNOCKBACK":2,"DURABILITY":3,"ARROW_FIRE":1,"ARROW_INFINITE":1},"repair-cost":7}},"2":{"==":"org.bukkit.inventory.ItemStack","type":"ARROW","amount":64},"3":{"==":"org.bukkit.inventory.ItemStack","type":"DIAMOND_BOOTS","damage":236,"meta":{"==":"ItemMeta","meta-type":"UNSPECIFIC","enchants":{"PROTECTION_ENVIRONMENTAL":5,"PROTECTION_FIRE":5,"DURABILITY":5,"PROTECTION_FALL":5,"PROTECTION_EXPLOSIONS":5,"PROTECTION_PROJECTILE":5,"THORNS":5}}},"4":{"==":"org.bukkit.inventory.ItemStack","type":"DIAMOND_LEGGINGS","damage":105,"meta":{"==":"ItemMeta","meta-type":"UNSPECIFIC","enchants":{"PROTECTION_ENVIRONMENTAL":5,"PROTECTION_FIRE":5,"DURABILITY":5,"PROTECTION_EXPLOSIONS":5,"PROTECTION_PROJECTILE":5,"THORNS":5}}},"5":{"==":"org.bukkit.inventory.ItemStack","type":"NETHER_STAR"},"6":{"==":"org.bukkit.inventory.ItemStack","type":"DIAMOND_SWORD","damage":1,"meta":{"==":"ItemMeta","meta-type":"UNSPECIFIC","lore":["§6Elemental X","§bWater-Infused X","§4Fire-Infused X"],"enchants":{"DAMAGE_ALL":5,"DURABILITY":3,"KNOCKBACK":2,"FIRE_ASPECT":2},"repair-cost":7}},"7":{"==":"org.bukkit.inventory.ItemStack","type":"DIAMOND_CHESTPLATE","damage":103,"meta":{"==":"ItemMeta","meta-type":"UNSPECIFIC","enchants":{"PROTECTION_ENVIRONMENTAL":5,"PROTECTION_FIRE":5,"DURABILITY":5,"PROTECTION_EXPLOSIONS":5,"PROTECTION_PROJECTILE":5,"THORNS":5}}},"8":{"==":"org.bukkit.inventory.ItemStack","type":"DIAMOND_PICKAXE","damage":25,"meta":{"==":"ItemMeta","meta-type":"UNSPECIFIC","display-name":"§6Emerald Pickaxe","lore":[""],"enchants":{"DIG_SPEED":6,"DURABILITY":6,"LOOT_BONUS_BLOCKS":10}}},"9":{"==":"org.bukkit.inventory.ItemStack","type":"DIAMOND_HELMET","damage":97,"meta":{"==":"ItemMeta","meta-type":"UNSPECIFIC","enchants":{"PROTECTION_ENVIRONMENTAL":5,"PROTECTION_FIRE":5,"DURABILITY":5,"PROTECTION_EXPLOSIONS":5,"PROTECTION_PROJECTILE":5,"WATER_WORKER":5,"THORNS":5}}}},"stats":{"ma":"300","el":"0","hp":"20","xp":"0.0","txp":"0","ft":"-20","fd":"0.0","ra":"300"}}}